{
  "data": [
    {
      "colorbar": {
        "title": {
          "text": "Density"
        }
      },
      "hovertemplate": "Time: %{x}<br>Space: %{y}<br>Density: %{z}<extra></extra>",
      "x": [
        "(748.0, 750.0]",
        "(750.0, 752.0]",
        "(752.0, 754.0]",
        "(754.0, 756.0]",
        "(756.0, 758.0]",
        "(758.0, 760.0]",
        "(760.0, 762.0]",
        "(762.0, 764.0]",
        "(764.0, 766.0]",
        "(766.0, 768.0]",
        "(768.0, 770.0]",
        "(770.0, 772.0]",
        "(772.0, 774.0]",
        "(774.0, 776.0]",
        "(776.0, 778.0]",
        "(778.0, 780.0]"
      ],
      "xgap": 2,
      "y": [
        "(0.0, 20.0]",
        "(20.0, 40.0]",
        "(40.0, 60.0]",
        "(60.0, 80.0]",
        "(80.0, 100.0]"
      ],
      "ygap": 2,
      "z": [
        [
          0.0625,
          0.059924448553689655,
          0.07896913288537241,
          0.09039758644286229,
          0.09143684276237837,
          0.0864829112651195,
          0.04568209487332743,
          0.006610738318047656,
          0.0009566518617608304,
          0.00013843881584481516,
          2.0033730658547665e-05,
          2.8991172862178477e-06,
          4.1953648985797246e-07,
          6.071188190939671e-08,
          8.785725900095947e-09,
          1.271398236457398e-09
        ],
        [
          0.05625,
          0.09556372671863907,
          0.10035577433539634,
          0.09234239920062999,
          0.08216630093737176,
          0.07364737480447264,
          0.06792574705586657,
          0.05985610983833804,
          0.018264986793929287,
          0.0034613722182805628,
          0.0006193065000592809,
          0.00010675557366126556,
          1.7928372350788937e-05,
          2.9532716973001447e-06,
          4.792994283402695e-07,
          7.687461215876518e-08
        ],
        [
          0.13125,
          0.10453132707467003,
          0.08535994135154804,
          0.07329935336579921,
          0.0662244048770645,
          0.06294020427134743,
          0.06178268115233099,
          0.061587657005400996,
          0.061001105965885156,
          0.028254940208929033,
          0.007049294147241814,
          0.0015498016063294918,
          0.0003155813669905557,
          6.1002273900247694e-05,
          1.1353647473664064e-05,
          2.0529459414072915e-06
        ],
        [
          0.08125,
          0.06865494620669091,
          0.06279035486898907,
          0.0600596454871428,
          0.06007851466968904,
          0.06077407288778032,
          0.061417722631608385,
          0.0604900144668755,
          0.059486534915686624,
          0.05875317611234575,
          0.03369403194324762,
          0.01090510219656209,
          0.002903624023190993,
          0.0006901016862431537,
          0.0001520403841832491,
          3.171267881375622e-05
        ],
        [
          0.05,
          0.056568819220137796,
          0.05751940489365619,
          0.06009495633996653,
          0.06138014783843799,
          0.06197856711102797,
          0.05968165556097669,
          0.058612152579810076,
          0.058114163605572575,
          0.05788228672179652,
          0.05777431869035162,
          0.03725919745208202,
          0.01471885083979399,
          0.004613426799738933,
          0.001257853137525407,
          0.00031206454159931013
        ]
      ],
      "zmax": 0.2,
      "zmin": 0,
      "type": "heatmap"
    }
  ],
  "layout": {
    "template": {
      "data": {
        "histogram2dcontour": [
          {
            "type": "histogram2dcontour",
            "colorbar": {
              "outlinewidth": 0,
              "ticks": ""
            },
            "colorscale": [
              [
                0.0,
                "#0d0887"
              ],
              [
                0.1111111111111111,
                "#46039f"
              ],
              [
                0.2222222222222222,
                "#7201a8"
              ],
              [
                0.3333333333333333,
                "#9c179e"
              ],
              [
                0.4444444444444444,
                "#bd3786"
              ],
              [
                0.5555555555555556,
                "#d8576b"
              ],
              [
                0.6666666666666666,
                "#ed7953"
              ],
              [
                0.7777777777777778,
                "#fb9f3a"
              ],
              [
                0.8888888888888888,
                "#fdca26"
              ],
              [
                1.0,
                "#f0f921"
              ]
            ]
          }
        ],
        "choropleth": [
          {
            "type": "choropleth",
            "colorbar": {
              "outlinewidth": 0,
              "ticks": ""
            }
          }
        ],
        "histogram2d": [
          {
            "type": "histogram2d",
            "colorbar": {
              "outlinewidth": 0,
              "ticks": ""
            },
            "colorscale": [
              [
                0.0,
                "#0d0887"
              ],
              [
                0.1111111111111111,
                "#46039f"
              ],
              [
                0.2222222222222222,
                "#7201a8"
              ],
              [
                0.3333333333333333,
                "#9c179e"
              ],
              [
                0.4444444444444444,
                "#bd3786"
              ],
              [
                0.5555555555555556,
                "#d8576b"
              ],
              [
                0.6666666666666666,
                "#ed7953"
              ],
              [
                0.7777777777777778,
                "#fb9f3a"
              ],
              [
                0.8888888888888888,
                "#fdca26"
              ],
              [
                1.0,
                "#f0f921"
              ]
            ]
          }
        ],
        "heatmap": [
          {
            "type": "heatmap",
            "colorbar": {
              "outlinewidth": 0,
              "ticks": ""
            },
            "colorscale": [
              [
                0.0,
                "#0d0887"
              ],
              [
                0.1111111111111111,
                "#46039f"
              ],
              [
                0.2222222222222222,
                "#7201a8"
              ],
              [
                0.3333333333333333,
                "#9c179e"
              ],
              [
                0.4444444444444444,
                "#bd3786"
              ],
              [
                0.5555555555555556,
                "#d8576b"
              ],
              [
                0.6666666666666666,
                "#ed7953"
              ],
              [
                0.7777777777777778,
                "#fb9f3a"
              ],
              [
                0.8888888888888888,
                "#fdca26"
              ],
              [
                1.0,
                "#f0f921"
              ]
            ]
          }
        ],
        "heatmapgl": [
          {
            "type": "heatmapgl",
            "colorbar": {
              "outlinewidth": 0,
              "ticks": ""
            },
            "colorscale": [
              [
                0.0,
                "#0d0887"
              ],
              [
                0.1111111111111111,
                "#46039f"
              ],
              [
                0.2222222222222222,
                "#7201a8"
              ],
              [
                0.3333333333333333,
                "#9c179e"
              ],
              [
                0.4444444444444444,
                "#bd3786"
              ],
              [
                0.5555555555555556,
                "#d8576b"
              ],
              [
                0.6666666666666666,
                "#ed7953"
              ],
              [
                0.7777777777777778,
                "#fb9f3a"
              ],
              [
                0.8888888888888888,
                "#fdca26"
              ],
              [
                1.0,
                "#f0f921"
              ]
            ]
          }
        ],
        "contourcarpet": [
          {
            "type": "contourcarpet",
            "colorbar": {
              "outlinewidth": 0,
              "ticks": ""
            }
          }
        ],
        "contour": [
          {
            "type": "contour",
            "colorbar": {
              "outlinewidth": 0,
              "ticks": ""
            },
            "colorscale": [
              [
                0.0,
                "#0d0887"
              ],
              [
                0.1111111111111111,
                "#46039f"
              ],
              [
                0.2222222222222222,
                "#7201a8"
              ],
              [
                0.3333333333333333,
                "#9c179e"
              ],
              [
                0.4444444444444444,
                "#bd3786"
              ],
              [
                0.5555555555555556,
                "#d8576b"
              ],
              [
                0.6666666666666666,
                "#ed7953"
              ],
              [
                0.7777777777777778,
                "#fb9f3a"
              ],
              [
                0.8888888888888888,
                "#fdca26"
              ],
              [
                1.0,
                "#f0f921"
              ]
            ]
          }
        ],
        "surface": [
          {
            "type": "surface",
            "colorbar": {
              "outlinewidth": 0,
              "ticks": ""
            },
            "colorscale": [
              [
                0.0,
                "#0d0887"
              ],
              [
                0.1111111111111111,
                "#46039f"
              ],
              [
                0.2222222222222222,
                "#7201a8"
              ],
              [
                0.3333333333333333,
                "#9c179e"
              ],
              [
                0.4444444444444444,
                "#bd3786"
              ],
              [
                0.5555555555555556,
                "#d8576b"
              ],
              [
                0.6666666666666666,
                "#ed7953"
              ],
              [
                0.7777777777777778,
                "#fb9f3a"
              ],
              [
                0.8888888888888888,
                "#fdca26"
              ],
              [
                1.0,
                "#f0f921"
              ]
            ]
          }
        ],
        "mesh3d": [
          {
            "type": "mesh3d",
            "colorbar": {
              "outlinewidth": 0,
              "ticks": ""
            }
          }
        ],
        "scatter": [
          {
            "fillpattern": {
              "fillmode": "overlay",
              "size": 10,
              "solidity": 0.2
            },
            "type": "scatter"
          }
        ],
        "parcoords": [
          {
            "type": "parcoords",
            "line": {
              "colorbar": {
                "outlinewidth": 0,
                "ticks": ""
              }
            }
          }
        ],
        "scatterpolargl": [
          {
            "type": "scatterpolargl",
            "marker": {
              "colorbar": {
                "outlinewidth": 0,
                "ticks": ""
              }
            }
          }
        ],
        "bar": [
          {
            "error_x": {
              "color": "#2a3f5f"
            },
            "error_y": {
              "color": "#2a3f5f"
            },
            "marker": {
              "line": {
                "color": "#E5ECF6",
                "width": 0.5
              },
              "pattern": {
                "fillmode": "overlay",
                "size": 10,
                "solidity": 0.2
              }
            },
            "type": "bar"
          }
        ],
        "scattergeo": [
          {
            "type": "scattergeo",
            "marker": {
              "colorbar": {
                "outlinewidth": 0,
                "ticks": ""
              }
            }
          }
        ],
        "scatterpolar": [
          {
            "type": "scatterpolar",
            "marker": {
              "colorbar": {
                "outlinewidth": 0,
                "ticks": ""
              }
            }
          }
        ],
        "histogram": [
          {
            "marker": {
              "pattern": {
                "fillmode": "overlay",
                "size": 10,
                "solidity": 0.2
              }
            },
            "type": "histogram"
          }
        ],
        "scattergl": [
          {
            "type": "scattergl",
            "marker": {
              "colorbar": {
                "outlinewidth": 0,
                "ticks": ""
              }
            }
          }
        ],
        "scatter3d": [
          {
            "type": "scatter3d",
            "line": {
              "colorbar": {
                "outlinewidth": 0,
                "ticks": ""
              }
            },
            "marker": {
              "colorbar": {
                "outlinewidth": 0,
                "ticks": ""
              }
            }
          }
        ],
        "scattermapbox": [
          {
            "type": "scattermapbox",
            "marker": {
              "colorbar": {
                "outlinewidth": 0,
                "ticks": ""
              }
            }
          }
        ],
        "scatterternary": [
          {
            "type": "scatterternary",
            "marker": {
              "colorbar": {
                "outlinewidth": 0,
                "ticks": ""
              }
            }
          }
        ],
        "scattercarpet": [
          {
            "type": "scattercarpet",
            "marker": {
              "colorbar": {
                "outlinewidth": 0,
                "ticks": ""
              }
            }
          }
        ],
        "carpet": [
          {
            "aaxis": {
              "endlinecolor": "#2a3f5f",
              "gridcolor": "white",
              "linecolor": "white",
              "minorgridcolor": "white",
              "startlinecolor": "#2a3f5f"
            },
            "baxis": {
              "endlinecolor": "#2a3f5f",
              "gridcolor": "white",
              "linecolor": "white",
              "minorgridcolor": "white",
              "startlinecolor": "#2a3f5f"
            },
            "type": "carpet"
          }
        ],
        "table": [
          {
            "cells": {
              "fill": {
                "color": "#EBF0F8"
              },
              "line": {
                "color": "white"
              }
            },
            "header": {
              "fill": {
                "color": "#C8D4E3"
              },
              "line": {
                "color": "white"
              }
            },
            "type": "table"
          }
        ],
        "barpolar": [
          {
            "marker": {
              "line": {
                "color": "#E5ECF6",
                "width": 0.5
              },
              "pattern": {
                "fillmode": "overlay",
                "size": 10,
                "solidity": 0.2
              }
            },
            "type": "barpolar"
          }
        ],
        "pie": [
          {
            "automargin": true,
            "type": "pie"
          }
        ]
      },
      "layout": {
        "autotypenumbers": "strict",
        "colorway": [
          "#636efa",
          "#EF553B",
          "#00cc96",
          "#ab63fa",
          "#FFA15A",
          "#19d3f3",
          "#FF6692",
          "#B6E880",
          "#FF97FF",
          "#FECB52"
        ],
        "font": {
          "color": "#2a3f5f"
        },
        "hovermode": "closest",
        "hoverlabel": {
          "align": "left"
        },
        "paper_bgcolor": "white",
        "plot_bgcolor": "#E5ECF6",
        "polar": {
          "bgcolor": "#E5ECF6",
          "angularaxis": {
            "gridcolor": "white",
            "linecolor": "white",
            "ticks": ""
          },
          "radialaxis": {
            "gridcolor": "white",
            "linecolor": "white",
            "ticks": ""
          }
        },
        "ternary": {
          "bgcolor": "#E5ECF6",
          "aaxis": {
            "gridcolor": "white",
            "linecolor": "white",
            "ticks": ""
          },
          "baxis": {
            "gridcolor": "white",
            "linecolor": "white",
            "ticks": ""
          },
          "caxis": {
            "gridcolor": "white",
            "linecolor": "white",
            "ticks": ""
          }
        },
        "coloraxis": {
          "colorbar": {
            "outlinewidth": 0,
            "ticks": ""
          }
        },
        "colorscale": {
          "sequential": [
            [
              0.0,
              "#0d0887"
            ],
            [
              0.1111111111111111,
              "#46039f"
            ],
            [
              0.2222222222222222,
              "#7201a8"
            ],
            [
              0.3333333333333333,
              "#9c179e"
            ],
            [
              0.4444444444444444,
              "#bd3786"
            ],
            [
              0.5555555555555556,
              "#d8576b"
            ],
            [
              0.6666666666666666,
              "#ed7953"
            ],
            [
              0.7777777777777778,
              "#fb9f3a"
            ],
            [
              0.8888888888888888,
              "#fdca26"
            ],
            [
              1.0,
              "#f0f921"
            ]
          ],
          "sequentialminus": [
            [
              0.0,
              "#0d0887"
            ],
            [
              0.1111111111111111,
              "#46039f"
            ],
            [
              0.2222222222222222,
              "#7201a8"
            ],
            [
              0.3333333333333333,
              "#9c179e"
            ],
            [
              0.4444444444444444,
              "#bd3786"
            ],
            [
              0.5555555555555556,
              "#d8576b"
            ],
            [
              0.6666666666666666,
              "#ed7953"
            ],
            [
              0.7777777777777778,
              "#fb9f3a"
            ],
            [
              0.8888888888888888,
              "#fdca26"
            ],
            [
              1.0,
              "#f0f921"
            ]
          ],
          "diverging": [
            [
              0,
              "#8e0152"
            ],
            [
              0.1,
              "#c51b7d"
            ],
            [
              0.2,
              "#de77ae"
            ],
            [
              0.3,
              "#f1b6da"
            ],
            [
              0.4,
              "#fde0ef"
            ],
            [
              0.5,
              "#f7f7f7"
            ],
            [
              0.6,
              "#e6f5d0"
            ],
            [
              0.7,
              "#b8e186"
            ],
            [
              0.8,
              "#7fbc41"
            ],
            [
              0.9,
              "#4d9221"
            ],
            [
              1,
              "#276419"
            ]
          ]
        },
        "xaxis": {
          "gridcolor": "white",
          "linecolor": "white",
          "ticks": "",
          "title": {
            "standoff": 15
          },
          "zerolinecolor": "white",
          "automargin": true,
          "zerolinewidth": 2
        },
        "yaxis": {
          "gridcolor": "white",
          "linecolor": "white",
          "ticks": "",
          "title": {
            "standoff": 15
          },
          "zerolinecolor": "white",
          "automargin": true,
          "zerolinewidth": 2
        },
        "scene": {
          "xaxis": {
            "backgroundcolor": "#E5ECF6",
            "gridcolor": "white",
            "linecolor": "white",
            "showbackground": true,
            "ticks": "",
            "zerolinecolor": "white",
            "gridwidth": 2
          },
          "yaxis": {
            "backgroundcolor": "#E5ECF6",
            "gridcolor": "white",
            "linecolor": "white",
            "showbackground": true,
            "ticks": "",
            "zerolinecolor": "white",
            "gridwidth": 2
          },
          "zaxis": {
            "backgroundcolor": "#E5ECF6",
            "gridcolor": "white",
            "linecolor": "white",
            "showbackground": true,
            "ticks": "",
            "zerolinecolor": "white",
            "gridwidth": 2
          }
        },
        "shapedefaults": {
          "line": {
            "color": "#2a3f5f"
          }
        },
        "annotationdefaults": {
          "arrowcolor": "#2a3f5f",
          "arrowhead": 0,
          "arrowwidth": 1
        },
        "geo": {
          "bgcolor": "white",
          "landcolor": "#E5ECF6",
          "subunitcolor": "white",
          "showland": true,
          "showlakes": true,
          "lakecolor": "white"
        },
        "title": {
          "x": 0.05
        },
        "mapbox": {
          "style": "light"
        }
      }
    },
    "xaxis": {
      "title": {
        "text": "Time [sec]"
      }
    },
    "yaxis": {
      "title": {
        "text": "Space [m]"
      }
    },
    "title": {
      "text": "CTM-Tri. FD-vf:8.55,rhoj:0.150,rhoc:0.058",
      "x": 0.5
    },
    "margin": {
      "r": 10,
      "t": 40,
      "l": 10,
      "b": 0
    },
    "paper_bgcolor": "rgba(0,0,0,0)",
    "plot_bgcolor": "rgba(0,0,0,0)"
  }
}