{
  "data": [
    {
      "colorbar": {
        "title": {
          "text": "Density"
        }
      },
      "hovertemplate": "Time: %{x}<br>Space: %{y}<br>Density: %{z}<extra></extra>",
      "x": [
        "(1051.0, 1053.0]",
        "(1053.0, 1055.0]",
        "(1055.0, 1057.0]",
        "(1057.0, 1059.0]",
        "(1059.0, 1061.0]",
        "(1061.0, 1063.0]",
        "(1063.0, 1065.0]",
        "(1065.0, 1067.0]",
        "(1067.0, 1069.0]",
        "(1069.0, 1071.0]",
        "(1071.0, 1073.0]",
        "(1073.0, 1075.0]",
        "(1075.0, 1077.0]",
        "(1077.0, 1079.0]",
        "(1079.0, 1081.0]"
      ],
      "xgap": 2,
      "y": [
        "(0.0, 20.0]",
        "(20.0, 40.0]",
        "(40.0, 60.0]",
        "(60.0, 80.0]",
        "(80.0, 100.0]"
      ],
      "ygap": 2,
      "z": [
        [
          0.1,
          0.1,
          0.0964305625855462,
          0.09024539406468086,
          0.0830244602761371,
          0.040390081102932414,
          0.005844921463356682,
          0.0008458291238817861,
          0.00012240145762296823,
          1.7712935633463957e-05,
          2.563270853535681e-06,
          3.7093554702319177e-07,
          5.3678751839901576e-08,
          7.767948966372813e-09,
          1.1241139012349118e-09
        ],
        [
          0.1,
          0.09332033176866751,
          0.08485594483010811,
          0.07673249653282375,
          0.07021613630970006,
          0.06554275971990517,
          0.051846390749801206,
          0.012501877028587328,
          0.0025325968330751417,
          0.0004711851762038322,
          8.333572121766418e-05,
          1.4251997785726244e-05,
          2.379689092390422e-06,
          3.9027990222695235e-07,
          6.312194342618903e-08
        ],
        [
          0.0875,
          0.07748049765300126,
          0.06965412638652979,
          0.06453810304379304,
          0.06147061103070237,
          0.059723194814916274,
          0.05876096511864685,
          0.054566909603494106,
          0.01858918373954168,
          0.0048561744757812005,
          0.0011057448842760297,
          0.00023129039469957802,
          4.566001554289284e-05,
          8.642863171366444e-06,
          1.584526107254495e-06
        ],
        [
          0.06875,
          0.0628346144380234,
          0.060080253917200246,
          0.0587977505538634,
          0.058200582948339206,
          0.05792252586148708,
          0.05916902626210412,
          0.05901414746487566,
          0.05664967378505558,
          0.024096985880516987,
          0.007640546987075152,
          0.002051407879408414,
          0.000494682877747429,
          0.00011063892356114394,
          2.340289697844767e-05
        ],
        [
          0.05625,
          0.0574732679894503,
          0.05765028930586593,
          0.0576759063797498,
          0.057679613472701424,
          0.06025516491901177,
          0.05887919375870604,
          0.05823850506613822,
          0.05794018340604394,
          0.05705875168756602,
          0.02886694244348536,
          0.010712256946673656,
          0.0033047349642227122,
          0.0009013305819580838,
          0.00022506133913598745
        ]
      ],
      "zmax": 0.2,
      "zmin": 0,
      "type": "heatmap"
    }
  ],
  "layout": {
    "template": {
      "data": {
        "histogram2dcontour": [
          {
            "type": "histogram2dcontour",
            "colorbar": {
              "outlinewidth": 0,
              "ticks": ""
            },
            "colorscale": [
              [
                0.0,
                "#0d0887"
              ],
              [
                0.1111111111111111,
                "#46039f"
              ],
              [
                0.2222222222222222,
                "#7201a8"
              ],
              [
                0.3333333333333333,
                "#9c179e"
              ],
              [
                0.4444444444444444,
                "#bd3786"
              ],
              [
                0.5555555555555556,
                "#d8576b"
              ],
              [
                0.6666666666666666,
                "#ed7953"
              ],
              [
                0.7777777777777778,
                "#fb9f3a"
              ],
              [
                0.8888888888888888,
                "#fdca26"
              ],
              [
                1.0,
                "#f0f921"
              ]
            ]
          }
        ],
        "choropleth": [
          {
            "type": "choropleth",
            "colorbar": {
              "outlinewidth": 0,
              "ticks": ""
            }
          }
        ],
        "histogram2d": [
          {
            "type": "histogram2d",
            "colorbar": {
              "outlinewidth": 0,
              "ticks": ""
            },
            "colorscale": [
              [
                0.0,
                "#0d0887"
              ],
              [
                0.1111111111111111,
                "#46039f"
              ],
              [
                0.2222222222222222,
                "#7201a8"
              ],
              [
                0.3333333333333333,
                "#9c179e"
              ],
              [
                0.4444444444444444,
                "#bd3786"
              ],
              [
                0.5555555555555556,
                "#d8576b"
              ],
              [
                0.6666666666666666,
                "#ed7953"
              ],
              [
                0.7777777777777778,
                "#fb9f3a"
              ],
              [
                0.8888888888888888,
                "#fdca26"
              ],
              [
                1.0,
                "#f0f921"
              ]
            ]
          }
        ],
        "heatmap": [
          {
            "type": "heatmap",
            "colorbar": {
              "outlinewidth": 0,
              "ticks": ""
            },
            "colorscale": [
              [
                0.0,
                "#0d0887"
              ],
              [
                0.1111111111111111,
                "#46039f"
              ],
              [
                0.2222222222222222,
                "#7201a8"
              ],
              [
                0.3333333333333333,
                "#9c179e"
              ],
              [
                0.4444444444444444,
                "#bd3786"
              ],
              [
                0.5555555555555556,
                "#d8576b"
              ],
              [
                0.6666666666666666,
                "#ed7953"
              ],
              [
                0.7777777777777778,
                "#fb9f3a"
              ],
              [
                0.8888888888888888,
                "#fdca26"
              ],
              [
                1.0,
                "#f0f921"
              ]
            ]
          }
        ],
        "heatmapgl": [
          {
            "type": "heatmapgl",
            "colorbar": {
              "outlinewidth": 0,
              "ticks": ""
            },
            "colorscale": [
              [
                0.0,
                "#0d0887"
              ],
              [
                0.1111111111111111,
                "#46039f"
              ],
              [
                0.2222222222222222,
                "#7201a8"
              ],
              [
                0.3333333333333333,
                "#9c179e"
              ],
              [
                0.4444444444444444,
                "#bd3786"
              ],
              [
                0.5555555555555556,
                "#d8576b"
              ],
              [
                0.6666666666666666,
                "#ed7953"
              ],
              [
                0.7777777777777778,
                "#fb9f3a"
              ],
              [
                0.8888888888888888,
                "#fdca26"
              ],
              [
                1.0,
                "#f0f921"
              ]
            ]
          }
        ],
        "contourcarpet": [
          {
            "type": "contourcarpet",
            "colorbar": {
              "outlinewidth": 0,
              "ticks": ""
            }
          }
        ],
        "contour": [
          {
            "type": "contour",
            "colorbar": {
              "outlinewidth": 0,
              "ticks": ""
            },
            "colorscale": [
              [
                0.0,
                "#0d0887"
              ],
              [
                0.1111111111111111,
                "#46039f"
              ],
              [
                0.2222222222222222,
                "#7201a8"
              ],
              [
                0.3333333333333333,
                "#9c179e"
              ],
              [
                0.4444444444444444,
                "#bd3786"
              ],
              [
                0.5555555555555556,
                "#d8576b"
              ],
              [
                0.6666666666666666,
                "#ed7953"
              ],
              [
                0.7777777777777778,
                "#fb9f3a"
              ],
              [
                0.8888888888888888,
                "#fdca26"
              ],
              [
                1.0,
                "#f0f921"
              ]
            ]
          }
        ],
        "surface": [
          {
            "type": "surface",
            "colorbar": {
              "outlinewidth": 0,
              "ticks": ""
            },
            "colorscale": [
              [
                0.0,
                "#0d0887"
              ],
              [
                0.1111111111111111,
                "#46039f"
              ],
              [
                0.2222222222222222,
                "#7201a8"
              ],
              [
                0.3333333333333333,
                "#9c179e"
              ],
              [
                0.4444444444444444,
                "#bd3786"
              ],
              [
                0.5555555555555556,
                "#d8576b"
              ],
              [
                0.6666666666666666,
                "#ed7953"
              ],
              [
                0.7777777777777778,
                "#fb9f3a"
              ],
              [
                0.8888888888888888,
                "#fdca26"
              ],
              [
                1.0,
                "#f0f921"
              ]
            ]
          }
        ],
        "mesh3d": [
          {
            "type": "mesh3d",
            "colorbar": {
              "outlinewidth": 0,
              "ticks": ""
            }
          }
        ],
        "scatter": [
          {
            "fillpattern": {
              "fillmode": "overlay",
              "size": 10,
              "solidity": 0.2
            },
            "type": "scatter"
          }
        ],
        "parcoords": [
          {
            "type": "parcoords",
            "line": {
              "colorbar": {
                "outlinewidth": 0,
                "ticks": ""
              }
            }
          }
        ],
        "scatterpolargl": [
          {
            "type": "scatterpolargl",
            "marker": {
              "colorbar": {
                "outlinewidth": 0,
                "ticks": ""
              }
            }
          }
        ],
        "bar": [
          {
            "error_x": {
              "color": "#2a3f5f"
            },
            "error_y": {
              "color": "#2a3f5f"
            },
            "marker": {
              "line": {
                "color": "#E5ECF6",
                "width": 0.5
              },
              "pattern": {
                "fillmode": "overlay",
                "size": 10,
                "solidity": 0.2
              }
            },
            "type": "bar"
          }
        ],
        "scattergeo": [
          {
            "type": "scattergeo",
            "marker": {
              "colorbar": {
                "outlinewidth": 0,
                "ticks": ""
              }
            }
          }
        ],
        "scatterpolar": [
          {
            "type": "scatterpolar",
            "marker": {
              "colorbar": {
                "outlinewidth": 0,
                "ticks": ""
              }
            }
          }
        ],
        "histogram": [
          {
            "marker": {
              "pattern": {
                "fillmode": "overlay",
                "size": 10,
                "solidity": 0.2
              }
            },
            "type": "histogram"
          }
        ],
        "scattergl": [
          {
            "type": "scattergl",
            "marker": {
              "colorbar": {
                "outlinewidth": 0,
                "ticks": ""
              }
            }
          }
        ],
        "scatter3d": [
          {
            "type": "scatter3d",
            "line": {
              "colorbar": {
                "outlinewidth": 0,
                "ticks": ""
              }
            },
            "marker": {
              "colorbar": {
                "outlinewidth": 0,
                "ticks": ""
              }
            }
          }
        ],
        "scattermapbox": [
          {
            "type": "scattermapbox",
            "marker": {
              "colorbar": {
                "outlinewidth": 0,
                "ticks": ""
              }
            }
          }
        ],
        "scatterternary": [
          {
            "type": "scatterternary",
            "marker": {
              "colorbar": {
                "outlinewidth": 0,
                "ticks": ""
              }
            }
          }
        ],
        "scattercarpet": [
          {
            "type": "scattercarpet",
            "marker": {
              "colorbar": {
                "outlinewidth": 0,
                "ticks": ""
              }
            }
          }
        ],
        "carpet": [
          {
            "aaxis": {
              "endlinecolor": "#2a3f5f",
              "gridcolor": "white",
              "linecolor": "white",
              "minorgridcolor": "white",
              "startlinecolor": "#2a3f5f"
            },
            "baxis": {
              "endlinecolor": "#2a3f5f",
              "gridcolor": "white",
              "linecolor": "white",
              "minorgridcolor": "white",
              "startlinecolor": "#2a3f5f"
            },
            "type": "carpet"
          }
        ],
        "table": [
          {
            "cells": {
              "fill": {
                "color": "#EBF0F8"
              },
              "line": {
                "color": "white"
              }
            },
            "header": {
              "fill": {
                "color": "#C8D4E3"
              },
              "line": {
                "color": "white"
              }
            },
            "type": "table"
          }
        ],
        "barpolar": [
          {
            "marker": {
              "line": {
                "color": "#E5ECF6",
                "width": 0.5
              },
              "pattern": {
                "fillmode": "overlay",
                "size": 10,
                "solidity": 0.2
              }
            },
            "type": "barpolar"
          }
        ],
        "pie": [
          {
            "automargin": true,
            "type": "pie"
          }
        ]
      },
      "layout": {
        "autotypenumbers": "strict",
        "colorway": [
          "#636efa",
          "#EF553B",
          "#00cc96",
          "#ab63fa",
          "#FFA15A",
          "#19d3f3",
          "#FF6692",
          "#B6E880",
          "#FF97FF",
          "#FECB52"
        ],
        "font": {
          "color": "#2a3f5f"
        },
        "hovermode": "closest",
        "hoverlabel": {
          "align": "left"
        },
        "paper_bgcolor": "white",
        "plot_bgcolor": "#E5ECF6",
        "polar": {
          "bgcolor": "#E5ECF6",
          "angularaxis": {
            "gridcolor": "white",
            "linecolor": "white",
            "ticks": ""
          },
          "radialaxis": {
            "gridcolor": "white",
            "linecolor": "white",
            "ticks": ""
          }
        },
        "ternary": {
          "bgcolor": "#E5ECF6",
          "aaxis": {
            "gridcolor": "white",
            "linecolor": "white",
            "ticks": ""
          },
          "baxis": {
            "gridcolor": "white",
            "linecolor": "white",
            "ticks": ""
          },
          "caxis": {
            "gridcolor": "white",
            "linecolor": "white",
            "ticks": ""
          }
        },
        "coloraxis": {
          "colorbar": {
            "outlinewidth": 0,
            "ticks": ""
          }
        },
        "colorscale": {
          "sequential": [
            [
              0.0,
              "#0d0887"
            ],
            [
              0.1111111111111111,
              "#46039f"
            ],
            [
              0.2222222222222222,
              "#7201a8"
            ],
            [
              0.3333333333333333,
              "#9c179e"
            ],
            [
              0.4444444444444444,
              "#bd3786"
            ],
            [
              0.5555555555555556,
              "#d8576b"
            ],
            [
              0.6666666666666666,
              "#ed7953"
            ],
            [
              0.7777777777777778,
              "#fb9f3a"
            ],
            [
              0.8888888888888888,
              "#fdca26"
            ],
            [
              1.0,
              "#f0f921"
            ]
          ],
          "sequentialminus": [
            [
              0.0,
              "#0d0887"
            ],
            [
              0.1111111111111111,
              "#46039f"
            ],
            [
              0.2222222222222222,
              "#7201a8"
            ],
            [
              0.3333333333333333,
              "#9c179e"
            ],
            [
              0.4444444444444444,
              "#bd3786"
            ],
            [
              0.5555555555555556,
              "#d8576b"
            ],
            [
              0.6666666666666666,
              "#ed7953"
            ],
            [
              0.7777777777777778,
              "#fb9f3a"
            ],
            [
              0.8888888888888888,
              "#fdca26"
            ],
            [
              1.0,
              "#f0f921"
            ]
          ],
          "diverging": [
            [
              0,
              "#8e0152"
            ],
            [
              0.1,
              "#c51b7d"
            ],
            [
              0.2,
              "#de77ae"
            ],
            [
              0.3,
              "#f1b6da"
            ],
            [
              0.4,
              "#fde0ef"
            ],
            [
              0.5,
              "#f7f7f7"
            ],
            [
              0.6,
              "#e6f5d0"
            ],
            [
              0.7,
              "#b8e186"
            ],
            [
              0.8,
              "#7fbc41"
            ],
            [
              0.9,
              "#4d9221"
            ],
            [
              1,
              "#276419"
            ]
          ]
        },
        "xaxis": {
          "gridcolor": "white",
          "linecolor": "white",
          "ticks": "",
          "title": {
            "standoff": 15
          },
          "zerolinecolor": "white",
          "automargin": true,
          "zerolinewidth": 2
        },
        "yaxis": {
          "gridcolor": "white",
          "linecolor": "white",
          "ticks": "",
          "title": {
            "standoff": 15
          },
          "zerolinecolor": "white",
          "automargin": true,
          "zerolinewidth": 2
        },
        "scene": {
          "xaxis": {
            "backgroundcolor": "#E5ECF6",
            "gridcolor": "white",
            "linecolor": "white",
            "showbackground": true,
            "ticks": "",
            "zerolinecolor": "white",
            "gridwidth": 2
          },
          "yaxis": {
            "backgroundcolor": "#E5ECF6",
            "gridcolor": "white",
            "linecolor": "white",
            "showbackground": true,
            "ticks": "",
            "zerolinecolor": "white",
            "gridwidth": 2
          },
          "zaxis": {
            "backgroundcolor": "#E5ECF6",
            "gridcolor": "white",
            "linecolor": "white",
            "showbackground": true,
            "ticks": "",
            "zerolinecolor": "white",
            "gridwidth": 2
          }
        },
        "shapedefaults": {
          "line": {
            "color": "#2a3f5f"
          }
        },
        "annotationdefaults": {
          "arrowcolor": "#2a3f5f",
          "arrowhead": 0,
          "arrowwidth": 1
        },
        "geo": {
          "bgcolor": "white",
          "landcolor": "#E5ECF6",
          "subunitcolor": "white",
          "showland": true,
          "showlakes": true,
          "lakecolor": "white"
        },
        "title": {
          "x": 0.05
        },
        "mapbox": {
          "style": "light"
        }
      }
    },
    "xaxis": {
      "title": {
        "text": "Time [sec]"
      }
    },
    "yaxis": {
      "title": {
        "text": "Space [m]"
      }
    },
    "title": {
      "text": "CTM-Tri. FD-vf:8.55,rhoj:0.150,rhoc:0.058",
      "x": 0.5
    },
    "margin": {
      "r": 10,
      "t": 40,
      "l": 10,
      "b": 0
    },
    "paper_bgcolor": "rgba(0,0,0,0)",
    "plot_bgcolor": "rgba(0,0,0,0)"
  }
}