{
  "data": [
    {
      "colorbar": {
        "title": {
          "text": "Density"
        }
      },
      "hovertemplate": "Time: %{x}<br>Space: %{y}<br>Density: %{z}<extra></extra>",
      "x": [
        "(440.5, 441.5]",
        "(441.5, 442.5]",
        "(442.5, 443.5]",
        "(443.5, 444.5]",
        "(444.5, 445.5]",
        "(445.5, 446.5]",
        "(446.5, 447.5]",
        "(447.5, 448.5]",
        "(448.5, 449.5]",
        "(449.5, 450.5]",
        "(450.5, 451.5]",
        "(451.5, 452.5]",
        "(452.5, 453.5]",
        "(453.5, 454.5]",
        "(454.5, 455.5]",
        "(455.5, 456.5]"
      ],
      "y": [
        "(0.0, 20.0]",
        "(20.0, 40.0]",
        "(40.0, 60.0]",
        "(60.0, 80.0]",
        "(80.0, 100.0]"
      ],
      "z": [
        [
          0.032925150718211185,
          0.10151294972567067,
          0.09654561313143571,
          0.07070719157065976,
          0.02033513594497248,
          0.08851919911613634,
          0.14440461384090456,
          0.03393227161650485,
          0.04439366859783767,
          0.06552147075269873,
          0.0439356967097244,
          0.06990196221420443,
          0.021530102095425253,
          0.10093440523036415,
          0.045318022914741865,
          0.0031396572423155675
        ],
        [
          0.08535582959498107,
          0.042227478862256966,
          0.0887303712392544,
          0.09437364817943229,
          0.07656750936698768,
          0.028508734550117328,
          0.07798484811636663,
          0.12224802989669259,
          0.05462204425135442,
          0.0459128234577711,
          0.06224385709510029,
          0.04685162516078398,
          0.06586514790242023,
          0.027342110713377638,
          null,
          null
        ],
        [
          0.10150431974482413,
          0.08988209351649915,
          0.051670925008026475,
          0.08092557980564818,
          0.0908374941737099,
          0.08015080965263023,
          0.036925841063601986,
          0.07090766992014907,
          0.10737300515651585,
          0.06744013602857081,
          0.04957310034230261,
          0.06011864889230939,
          null,
          null,
          null,
          null
        ],
        [
          0.0975344606991706,
          0.10031908589035196,
          0.09285978590494981,
          0.06060050802871851,
          0.07661078796533584,
          0.08726413790107622,
          0.08193712586609907,
          0.04495110334901583,
          0.06639672597833271,
          null,
          null,
          null,
          null,
          null,
          null,
          null
        ],
        [
          0.0954795893101752,
          0.0969395321256131,
          0.0993191167326374,
          0.09472180657030702,
          0.06855020662862434,
          0.07485566495957201,
          null,
          null,
          null,
          null,
          null,
          null,
          null,
          null,
          null,
          null
        ]
      ],
      "zmax": 0.5,
      "zmin": 0,
      "type": "heatmap"
    }
  ],
  "layout": {
    "template": {
      "data": {
        "histogram2dcontour": [
          {
            "type": "histogram2dcontour",
            "colorbar": {
              "outlinewidth": 0,
              "ticks": ""
            },
            "colorscale": [
              [
                0.0,
                "#0d0887"
              ],
              [
                0.1111111111111111,
                "#46039f"
              ],
              [
                0.2222222222222222,
                "#7201a8"
              ],
              [
                0.3333333333333333,
                "#9c179e"
              ],
              [
                0.4444444444444444,
                "#bd3786"
              ],
              [
                0.5555555555555556,
                "#d8576b"
              ],
              [
                0.6666666666666666,
                "#ed7953"
              ],
              [
                0.7777777777777778,
                "#fb9f3a"
              ],
              [
                0.8888888888888888,
                "#fdca26"
              ],
              [
                1.0,
                "#f0f921"
              ]
            ]
          }
        ],
        "choropleth": [
          {
            "type": "choropleth",
            "colorbar": {
              "outlinewidth": 0,
              "ticks": ""
            }
          }
        ],
        "histogram2d": [
          {
            "type": "histogram2d",
            "colorbar": {
              "outlinewidth": 0,
              "ticks": ""
            },
            "colorscale": [
              [
                0.0,
                "#0d0887"
              ],
              [
                0.1111111111111111,
                "#46039f"
              ],
              [
                0.2222222222222222,
                "#7201a8"
              ],
              [
                0.3333333333333333,
                "#9c179e"
              ],
              [
                0.4444444444444444,
                "#bd3786"
              ],
              [
                0.5555555555555556,
                "#d8576b"
              ],
              [
                0.6666666666666666,
                "#ed7953"
              ],
              [
                0.7777777777777778,
                "#fb9f3a"
              ],
              [
                0.8888888888888888,
                "#fdca26"
              ],
              [
                1.0,
                "#f0f921"
              ]
            ]
          }
        ],
        "heatmap": [
          {
            "type": "heatmap",
            "colorbar": {
              "outlinewidth": 0,
              "ticks": ""
            },
            "colorscale": [
              [
                0.0,
                "#0d0887"
              ],
              [
                0.1111111111111111,
                "#46039f"
              ],
              [
                0.2222222222222222,
                "#7201a8"
              ],
              [
                0.3333333333333333,
                "#9c179e"
              ],
              [
                0.4444444444444444,
                "#bd3786"
              ],
              [
                0.5555555555555556,
                "#d8576b"
              ],
              [
                0.6666666666666666,
                "#ed7953"
              ],
              [
                0.7777777777777778,
                "#fb9f3a"
              ],
              [
                0.8888888888888888,
                "#fdca26"
              ],
              [
                1.0,
                "#f0f921"
              ]
            ]
          }
        ],
        "heatmapgl": [
          {
            "type": "heatmapgl",
            "colorbar": {
              "outlinewidth": 0,
              "ticks": ""
            },
            "colorscale": [
              [
                0.0,
                "#0d0887"
              ],
              [
                0.1111111111111111,
                "#46039f"
              ],
              [
                0.2222222222222222,
                "#7201a8"
              ],
              [
                0.3333333333333333,
                "#9c179e"
              ],
              [
                0.4444444444444444,
                "#bd3786"
              ],
              [
                0.5555555555555556,
                "#d8576b"
              ],
              [
                0.6666666666666666,
                "#ed7953"
              ],
              [
                0.7777777777777778,
                "#fb9f3a"
              ],
              [
                0.8888888888888888,
                "#fdca26"
              ],
              [
                1.0,
                "#f0f921"
              ]
            ]
          }
        ],
        "contourcarpet": [
          {
            "type": "contourcarpet",
            "colorbar": {
              "outlinewidth": 0,
              "ticks": ""
            }
          }
        ],
        "contour": [
          {
            "type": "contour",
            "colorbar": {
              "outlinewidth": 0,
              "ticks": ""
            },
            "colorscale": [
              [
                0.0,
                "#0d0887"
              ],
              [
                0.1111111111111111,
                "#46039f"
              ],
              [
                0.2222222222222222,
                "#7201a8"
              ],
              [
                0.3333333333333333,
                "#9c179e"
              ],
              [
                0.4444444444444444,
                "#bd3786"
              ],
              [
                0.5555555555555556,
                "#d8576b"
              ],
              [
                0.6666666666666666,
                "#ed7953"
              ],
              [
                0.7777777777777778,
                "#fb9f3a"
              ],
              [
                0.8888888888888888,
                "#fdca26"
              ],
              [
                1.0,
                "#f0f921"
              ]
            ]
          }
        ],
        "surface": [
          {
            "type": "surface",
            "colorbar": {
              "outlinewidth": 0,
              "ticks": ""
            },
            "colorscale": [
              [
                0.0,
                "#0d0887"
              ],
              [
                0.1111111111111111,
                "#46039f"
              ],
              [
                0.2222222222222222,
                "#7201a8"
              ],
              [
                0.3333333333333333,
                "#9c179e"
              ],
              [
                0.4444444444444444,
                "#bd3786"
              ],
              [
                0.5555555555555556,
                "#d8576b"
              ],
              [
                0.6666666666666666,
                "#ed7953"
              ],
              [
                0.7777777777777778,
                "#fb9f3a"
              ],
              [
                0.8888888888888888,
                "#fdca26"
              ],
              [
                1.0,
                "#f0f921"
              ]
            ]
          }
        ],
        "mesh3d": [
          {
            "type": "mesh3d",
            "colorbar": {
              "outlinewidth": 0,
              "ticks": ""
            }
          }
        ],
        "scatter": [
          {
            "fillpattern": {
              "fillmode": "overlay",
              "size": 10,
              "solidity": 0.2
            },
            "type": "scatter"
          }
        ],
        "parcoords": [
          {
            "type": "parcoords",
            "line": {
              "colorbar": {
                "outlinewidth": 0,
                "ticks": ""
              }
            }
          }
        ],
        "scatterpolargl": [
          {
            "type": "scatterpolargl",
            "marker": {
              "colorbar": {
                "outlinewidth": 0,
                "ticks": ""
              }
            }
          }
        ],
        "bar": [
          {
            "error_x": {
              "color": "#2a3f5f"
            },
            "error_y": {
              "color": "#2a3f5f"
            },
            "marker": {
              "line": {
                "color": "#E5ECF6",
                "width": 0.5
              },
              "pattern": {
                "fillmode": "overlay",
                "size": 10,
                "solidity": 0.2
              }
            },
            "type": "bar"
          }
        ],
        "scattergeo": [
          {
            "type": "scattergeo",
            "marker": {
              "colorbar": {
                "outlinewidth": 0,
                "ticks": ""
              }
            }
          }
        ],
        "scatterpolar": [
          {
            "type": "scatterpolar",
            "marker": {
              "colorbar": {
                "outlinewidth": 0,
                "ticks": ""
              }
            }
          }
        ],
        "histogram": [
          {
            "marker": {
              "pattern": {
                "fillmode": "overlay",
                "size": 10,
                "solidity": 0.2
              }
            },
            "type": "histogram"
          }
        ],
        "scattergl": [
          {
            "type": "scattergl",
            "marker": {
              "colorbar": {
                "outlinewidth": 0,
                "ticks": ""
              }
            }
          }
        ],
        "scatter3d": [
          {
            "type": "scatter3d",
            "line": {
              "colorbar": {
                "outlinewidth": 0,
                "ticks": ""
              }
            },
            "marker": {
              "colorbar": {
                "outlinewidth": 0,
                "ticks": ""
              }
            }
          }
        ],
        "scattermapbox": [
          {
            "type": "scattermapbox",
            "marker": {
              "colorbar": {
                "outlinewidth": 0,
                "ticks": ""
              }
            }
          }
        ],
        "scatterternary": [
          {
            "type": "scatterternary",
            "marker": {
              "colorbar": {
                "outlinewidth": 0,
                "ticks": ""
              }
            }
          }
        ],
        "scattercarpet": [
          {
            "type": "scattercarpet",
            "marker": {
              "colorbar": {
                "outlinewidth": 0,
                "ticks": ""
              }
            }
          }
        ],
        "carpet": [
          {
            "aaxis": {
              "endlinecolor": "#2a3f5f",
              "gridcolor": "white",
              "linecolor": "white",
              "minorgridcolor": "white",
              "startlinecolor": "#2a3f5f"
            },
            "baxis": {
              "endlinecolor": "#2a3f5f",
              "gridcolor": "white",
              "linecolor": "white",
              "minorgridcolor": "white",
              "startlinecolor": "#2a3f5f"
            },
            "type": "carpet"
          }
        ],
        "table": [
          {
            "cells": {
              "fill": {
                "color": "#EBF0F8"
              },
              "line": {
                "color": "white"
              }
            },
            "header": {
              "fill": {
                "color": "#C8D4E3"
              },
              "line": {
                "color": "white"
              }
            },
            "type": "table"
          }
        ],
        "barpolar": [
          {
            "marker": {
              "line": {
                "color": "#E5ECF6",
                "width": 0.5
              },
              "pattern": {
                "fillmode": "overlay",
                "size": 10,
                "solidity": 0.2
              }
            },
            "type": "barpolar"
          }
        ],
        "pie": [
          {
            "automargin": true,
            "type": "pie"
          }
        ]
      },
      "layout": {
        "autotypenumbers": "strict",
        "colorway": [
          "#636efa",
          "#EF553B",
          "#00cc96",
          "#ab63fa",
          "#FFA15A",
          "#19d3f3",
          "#FF6692",
          "#B6E880",
          "#FF97FF",
          "#FECB52"
        ],
        "font": {
          "color": "#2a3f5f"
        },
        "hovermode": "closest",
        "hoverlabel": {
          "align": "left"
        },
        "paper_bgcolor": "white",
        "plot_bgcolor": "#E5ECF6",
        "polar": {
          "bgcolor": "#E5ECF6",
          "angularaxis": {
            "gridcolor": "white",
            "linecolor": "white",
            "ticks": ""
          },
          "radialaxis": {
            "gridcolor": "white",
            "linecolor": "white",
            "ticks": ""
          }
        },
        "ternary": {
          "bgcolor": "#E5ECF6",
          "aaxis": {
            "gridcolor": "white",
            "linecolor": "white",
            "ticks": ""
          },
          "baxis": {
            "gridcolor": "white",
            "linecolor": "white",
            "ticks": ""
          },
          "caxis": {
            "gridcolor": "white",
            "linecolor": "white",
            "ticks": ""
          }
        },
        "coloraxis": {
          "colorbar": {
            "outlinewidth": 0,
            "ticks": ""
          }
        },
        "colorscale": {
          "sequential": [
            [
              0.0,
              "#0d0887"
            ],
            [
              0.1111111111111111,
              "#46039f"
            ],
            [
              0.2222222222222222,
              "#7201a8"
            ],
            [
              0.3333333333333333,
              "#9c179e"
            ],
            [
              0.4444444444444444,
              "#bd3786"
            ],
            [
              0.5555555555555556,
              "#d8576b"
            ],
            [
              0.6666666666666666,
              "#ed7953"
            ],
            [
              0.7777777777777778,
              "#fb9f3a"
            ],
            [
              0.8888888888888888,
              "#fdca26"
            ],
            [
              1.0,
              "#f0f921"
            ]
          ],
          "sequentialminus": [
            [
              0.0,
              "#0d0887"
            ],
            [
              0.1111111111111111,
              "#46039f"
            ],
            [
              0.2222222222222222,
              "#7201a8"
            ],
            [
              0.3333333333333333,
              "#9c179e"
            ],
            [
              0.4444444444444444,
              "#bd3786"
            ],
            [
              0.5555555555555556,
              "#d8576b"
            ],
            [
              0.6666666666666666,
              "#ed7953"
            ],
            [
              0.7777777777777778,
              "#fb9f3a"
            ],
            [
              0.8888888888888888,
              "#fdca26"
            ],
            [
              1.0,
              "#f0f921"
            ]
          ],
          "diverging": [
            [
              0,
              "#8e0152"
            ],
            [
              0.1,
              "#c51b7d"
            ],
            [
              0.2,
              "#de77ae"
            ],
            [
              0.3,
              "#f1b6da"
            ],
            [
              0.4,
              "#fde0ef"
            ],
            [
              0.5,
              "#f7f7f7"
            ],
            [
              0.6,
              "#e6f5d0"
            ],
            [
              0.7,
              "#b8e186"
            ],
            [
              0.8,
              "#7fbc41"
            ],
            [
              0.9,
              "#4d9221"
            ],
            [
              1,
              "#276419"
            ]
          ]
        },
        "xaxis": {
          "gridcolor": "white",
          "linecolor": "white",
          "ticks": "",
          "title": {
            "standoff": 15
          },
          "zerolinecolor": "white",
          "automargin": true,
          "zerolinewidth": 2
        },
        "yaxis": {
          "gridcolor": "white",
          "linecolor": "white",
          "ticks": "",
          "title": {
            "standoff": 15
          },
          "zerolinecolor": "white",
          "automargin": true,
          "zerolinewidth": 2
        },
        "scene": {
          "xaxis": {
            "backgroundcolor": "#E5ECF6",
            "gridcolor": "white",
            "linecolor": "white",
            "showbackground": true,
            "ticks": "",
            "zerolinecolor": "white",
            "gridwidth": 2
          },
          "yaxis": {
            "backgroundcolor": "#E5ECF6",
            "gridcolor": "white",
            "linecolor": "white",
            "showbackground": true,
            "ticks": "",
            "zerolinecolor": "white",
            "gridwidth": 2
          },
          "zaxis": {
            "backgroundcolor": "#E5ECF6",
            "gridcolor": "white",
            "linecolor": "white",
            "showbackground": true,
            "ticks": "",
            "zerolinecolor": "white",
            "gridwidth": 2
          }
        },
        "shapedefaults": {
          "line": {
            "color": "#2a3f5f"
          }
        },
        "annotationdefaults": {
          "arrowcolor": "#2a3f5f",
          "arrowhead": 0,
          "arrowwidth": 1
        },
        "geo": {
          "bgcolor": "white",
          "landcolor": "#E5ECF6",
          "subunitcolor": "white",
          "showland": true,
          "showlakes": true,
          "lakecolor": "white"
        },
        "title": {
          "x": 0.05
        },
        "mapbox": {
          "style": "light"
        }
      }
    },
    "xaxis": {
      "title": {
        "text": "Time [sec]"
      }
    },
    "yaxis": {
      "title": {
        "text": "Space Interval [m]"
      }
    },
    "margin": {
      "r": 10,
      "t": 40,
      "l": 10,
      "b": 0
    },
    "title": {
      "text": "Best Model",
      "x": 0.5
    }
  }
}